jzdemopackage/__init__.py
jzdemopackage/functions.py
jzdemopackage/greet.py
jzdemopackage-0.1.1.dist-info/LICENSE
jzdemopackage-0.1.1.dist-info/METADATA
jzdemopackage-0.1.1.dist-info/WHEEL
jzdemopackage-0.1.1.dist-info/top_level.txt
jzdemopackage-0.1.1.dist-info/RECORD
