Metadata-Version: 2.1
Name: jzdemopackage
Version: 0.1.1
Summary: A example package
Author: Jiang Zhu
Author-email: Jiang Zhu <jzhu4@alaska.edu>
Project-URL: Homepage, https://github.com/pypa/sampleproject
Classifier: Programming Language :: Python :: 3
Classifier: License :: OSI Approved :: MIT License
Classifier: Operating System :: OS Independent
Requires-Python: >=3.11
License-File: LICENSE
